<?xml version="1.0" encoding="UTF-8"?>
<!DOCTYPE mapper PUBLIC "-//mybatis.org//DTD Mapper 3.0//EN" "http://mybatis.org/dtd/mybatis-3-mapper.dtd">
<mapper namespace="com.lanqiao.dao.TClassStatusLogMapper">
  <resultMap id="BaseResultMap" type="com.lanqiao.model.TClassStatusLog">
    <!--
      WARNING - @mbggenerated
      This element is automatically generated by MyBatis Generator, do not modify.
      This element was generated on Fri Dec 09 20:14:07 CST 2016.
    -->
    <id column="class_status_log_id" jdbcType="INTEGER" property="classStatusLogId" />
    <result column="class_id" jdbcType="INTEGER" property="classId" />
    <result column="begin_time" jdbcType="TIMESTAMP" property="beginTime" />
    <result column="operator_userid" jdbcType="INTEGER" property="operatorUserid" />
    <result column="remark" jdbcType="VARCHAR" property="remark" />
    <result column="newstatus" jdbcType="INTEGER" property="newstatus" />
    <result column="inputtime" jdbcType="TIMESTAMP" property="inputtime" />
    <result column="oldstatus" jdbcType="INTEGER" property="oldstatus" />
    <result column="end_time" jdbcType="TIMESTAMP" property="endTime" />
    <result column="finishcount" jdbcType="INTEGER" property="finishcount" />
  </resultMap>
  <sql id="Base_Column_List">
    <!--
      WARNING - @mbggenerated
      This element is automatically generated by MyBatis Generator, do not modify.
      This element was generated on Fri Dec 09 20:14:07 CST 2016.
    -->
    class_status_log_id, class_id, begin_time, operator_userid, remark, newstatus, inputtime, 
    oldstatus, end_time, finishcount
  </sql>
  <select id="selectByPrimaryKey" parameterType="java.lang.Integer" resultMap="BaseResultMap">
    <!--
      WARNING - @mbggenerated
      This element is automatically generated by MyBatis Generator, do not modify.
      This element was generated on Fri Dec 09 20:14:07 CST 2016.
    -->
    select 
    <include refid="Base_Column_List" />
    from t_class_status_log
    where class_status_log_id = #{classStatusLogId,jdbcType=INTEGER}
  </select>
  <delete id="deleteByPrimaryKey" parameterType="java.lang.Integer">
    <!--
      WARNING - @mbggenerated
      This element is automatically generated by MyBatis Generator, do not modify.
      This element was generated on Fri Dec 09 20:14:07 CST 2016.
    -->
    delete from t_class_status_log
    where class_status_log_id = #{classStatusLogId,jdbcType=INTEGER}
  </delete>
  <insert id="insert" keyProperty="classStatusLogId" parameterType="com.lanqiao.model.TClassStatusLog" useGeneratedKeys="true">
    <!--
      WARNING - @mbggenerated
      This element is automatically generated by MyBatis Generator, do not modify.
      This element was generated on Fri Dec 09 20:14:07 CST 2016.
    -->
    insert into t_class_status_log (class_id, begin_time, operator_userid, 
      remark, newstatus, inputtime, 
      oldstatus, end_time, finishcount
      )
    values (#{classId,jdbcType=INTEGER}, #{beginTime,jdbcType=TIMESTAMP}, #{operatorUserid,jdbcType=INTEGER}, 
      #{remark,jdbcType=VARCHAR}, #{newstatus,jdbcType=INTEGER}, #{inputtime,jdbcType=TIMESTAMP}, 
      #{oldstatus,jdbcType=INTEGER}, #{endTime,jdbcType=TIMESTAMP}, #{finishcount,jdbcType=INTEGER}
      )
  </insert>
  <insert id="insertSelective" keyProperty="classStatusLogId" parameterType="com.lanqiao.model.TClassStatusLog" useGeneratedKeys="true">
    <!--
      WARNING - @mbggenerated
      This element is automatically generated by MyBatis Generator, do not modify.
      This element was generated on Fri Dec 09 20:14:07 CST 2016.
    -->
    insert into t_class_status_log
    <trim prefix="(" suffix=")" suffixOverrides=",">
      <if test="classId != null">
        class_id,
      </if>
      <if test="beginTime != null">
        begin_time,
      </if>
      <if test="operatorUserid != null">
        operator_userid,
      </if>
      <if test="remark != null">
        remark,
      </if>
      <if test="newstatus != null">
        newstatus,
      </if>
      <if test="inputtime != null">
        inputtime,
      </if>
      <if test="oldstatus != null">
        oldstatus,
      </if>
      <if test="endTime != null">
        end_time,
      </if>
      <if test="finishcount != null">
        finishcount,
      </if>
    </trim>
    <trim prefix="values (" suffix=")" suffixOverrides=",">
      <if test="classId != null">
        #{classId,jdbcType=INTEGER},
      </if>
      <if test="beginTime != null">
        #{beginTime,jdbcType=TIMESTAMP},
      </if>
      <if test="operatorUserid != null">
        #{operatorUserid,jdbcType=INTEGER},
      </if>
      <if test="remark != null">
        #{remark,jdbcType=VARCHAR},
      </if>
      <if test="newstatus != null">
        #{newstatus,jdbcType=INTEGER},
      </if>
      <if test="inputtime != null">
        #{inputtime,jdbcType=TIMESTAMP},
      </if>
      <if test="oldstatus != null">
        #{oldstatus,jdbcType=INTEGER},
      </if>
      <if test="endTime != null">
        #{endTime,jdbcType=TIMESTAMP},
      </if>
      <if test="finishcount != null">
        #{finishcount,jdbcType=INTEGER},
      </if>
    </trim>
  </insert>
  <update id="updateByPrimaryKeySelective" parameterType="com.lanqiao.model.TClassStatusLog">
    <!--
      WARNING - @mbggenerated
      This element is automatically generated by MyBatis Generator, do not modify.
      This element was generated on Fri Dec 09 20:14:07 CST 2016.
    -->
    update t_class_status_log
    <set>
      <if test="classId != null">
        class_id = #{classId,jdbcType=INTEGER},
      </if>
      <if test="beginTime != null">
        begin_time = #{beginTime,jdbcType=TIMESTAMP},
      </if>
      <if test="operatorUserid != null">
        operator_userid = #{operatorUserid,jdbcType=INTEGER},
      </if>
      <if test="remark != null">
        remark = #{remark,jdbcType=VARCHAR},
      </if>
      <if test="newstatus != null">
        newstatus = #{newstatus,jdbcType=INTEGER},
      </if>
      <if test="inputtime != null">
        inputtime = #{inputtime,jdbcType=TIMESTAMP},
      </if>
      <if test="oldstatus != null">
        oldstatus = #{oldstatus,jdbcType=INTEGER},
      </if>
      <if test="endTime != null">
        end_time = #{endTime,jdbcType=TIMESTAMP},
      </if>
      <if test="finishcount != null">
        finishcount = #{finishcount,jdbcType=INTEGER},
      </if>
    </set>
    where class_status_log_id = #{classStatusLogId,jdbcType=INTEGER}
  </update>
  <update id="updateByPrimaryKey" parameterType="com.lanqiao.model.TClassStatusLog">
    <!--
      WARNING - @mbggenerated
      This element is automatically generated by MyBatis Generator, do not modify.
      This element was generated on Fri Dec 09 20:14:07 CST 2016.
    -->
    update t_class_status_log
    set class_id = #{classId,jdbcType=INTEGER},
      begin_time = #{beginTime,jdbcType=TIMESTAMP},
      operator_userid = #{operatorUserid,jdbcType=INTEGER},
      remark = #{remark,jdbcType=VARCHAR},
      newstatus = #{newstatus,jdbcType=INTEGER},
      inputtime = #{inputtime,jdbcType=TIMESTAMP},
      oldstatus = #{oldstatus,jdbcType=INTEGER},
      end_time = #{endTime,jdbcType=TIMESTAMP},
      finishcount = #{finishcount,jdbcType=INTEGER}
    where class_status_log_id = #{classStatusLogId,jdbcType=INTEGER}
  </update>
</mapper>